pystockdb/__init__.py
pystockdb/db/__init__.py
pystockdb/db/schema/__init__.py
pystockdb/db/schema/stocks.py
pystockdb/tools/__init__.py
pystockdb/tools/base.py
pystockdb/tools/create.py
pystockdb/tools/data_crawler.py
pystockdb/tools/fundamentals.py
pystockdb/tools/sync.py
pystockdb/tools/update.py
pystockdb-1.2.1.dist-info/LICENSE
pystockdb-1.2.1.dist-info/METADATA
pystockdb-1.2.1.dist-info/WHEEL
pystockdb-1.2.1.dist-info/RECORD
