Metadata-Version: 2.1
Name: pystockdb
Version: 1.2.1
Summary: Database for stocks this package provides an create, sync and update tool.
License: MIT
Author: SlashGordon
Author-email: slash.gordon.dev@gmail.com
Requires-Python: >=3.11,<4.0
Classifier: License :: OSI Approved :: MIT License
Classifier: Programming Language :: Python :: 3
Classifier: Programming Language :: Python :: 3.11
Classifier: Programming Language :: Python :: 3.12
Requires-Dist: pandas (>=2.1.3,<3.0.0)
Requires-Dist: pony (>=0.7.17,<0.8.0)
Requires-Dist: pytickersymbols (>=1.15.0,<2.0.0)
Requires-Dist: pyyaml (>=6.0.1,<7.0.0)
Requires-Dist: uplink (>=0.9.7,<0.10.0)
Requires-Dist: yfinance (>=0.2.32,<0.3.0)
